verysimplemodule_alison/__init__.py
verysimplemodule_alison/add.py
verysimplemodule_alison/subtract.py
verysimplemodule_alison/extra/__init__.py
verysimplemodule_alison/extra/divide.py
verysimplemodule_alison/extra/multiple.py
verysimplemodule_alisonVitor/__init__.py
verysimplemodule_alisonVitor/add.py
verysimplemodule_alisonVitor/subtract.py
verysimplemodule_alisonVitor/extra/__init__.py
verysimplemodule_alisonVitor/extra/divide.py
verysimplemodule_alisonVitor/extra/multiple.py
verysimplemodule_alisonVitor-0.1.8.dist-info/METADATA
verysimplemodule_alisonVitor-0.1.8.dist-info/WHEEL
verysimplemodule_alisonVitor-0.1.8.dist-info/top_level.txt
verysimplemodule_alisonVitor-0.1.8.dist-info/RECORD
