Metadata-Version: 2.1
Name: verysimplemodule-alisonVitor
Version: 0.1.8
Summary: My first Python package
Author: Alison
Author-email: alissonmarqueshm30@gmail.com
